{
  "title": "dress-graph: A Continuous Framework for Structural Graph Refinement",
  "description": "DRESS is a parameter-free algorithm that computes a unique, self-consistent edge similarity for any graph. Sorting the edge values produces a graph fingerprint that achieves 100% accuracy on standard isomorphism benchmarks.",
  "creators": [
    {
      "name": "Castrillo Velilla, Eduar"
    }
  ],
  "license": "MIT",
  "keywords": [
    "graph isomorphism",
    "graph similarity",
    "structural refinement",
    "Weisfeiler-Lehman",
    "graph fingerprint",
    "DRESS"
  ],
  "related_identifiers": [
    {
      "identifier": "arXiv:1805.01419",
      "relation": "isSupplementTo",
      "scheme": "arxiv"
    },
    {
      "identifier": "https://github.com/velicast/dress-graph",
      "relation": "isSupplementTo",
      "scheme": "url"
    }
  ],
  "upload_type": "software",
  "access_right": "open"
}
